README.md
setup.py
DataStoryPatternLibrary/DataStoryPatternLibrary.py
DataStoryPatternLibrary.egg-info/PKG-INFO
DataStoryPatternLibrary.egg-info/SOURCES.txt
DataStoryPatternLibrary.egg-info/dependency_links.txt
DataStoryPatternLibrary.egg-info/not-zip-safe
DataStoryPatternLibrary.egg-info/requires.txt
DataStoryPatternLibrary.egg-info/top_level.txt