Metadata-Version: 1.0
Name: DataStoryPatternLibrary
Version: 0.1.4.4
Summary: Data Story Pattern Analysis for LOSD
Home-page: https://github.com/MaciejJanowski/DataStoryPatternLibrary
Author: Maciej Janowski
Author-email: maciej.janowski@insight-centre.org
License: MIT
Platform: UNKNOWN
